{"344048874656366592":{"615535932988456970":{"groups":[],"perms":{"allow":["keiko.*"],"deny":[]}},"678566365799645185":{"groups":[],"perms":{"allow":["keiko.*"],"deny":[]}}},"465532814536736778":{"615535932988456970":{"groups":[],"perms":{"allow":[],"deny":[]}}},"517068183102816268":{"615535932988456970":{"groups":[],"perms":{"allow":["keiko.*"],"deny":[]}}},"637694863965683752":{"615535932988456970":{"groups":[],"perms":{"allow":["keiko.cc"],"deny":[]}}},"234739148286590976":{"615535932988456970":{"groups":[],"perms":{"allow":["keiko.cc","keiko.*"],"deny":[]}}},"620311379915833385":{"678566365799645185":{"groups":[],"perms":{"allow":["keiko.*"],"deny":[]}},"682660337996267542":{"groups":[],"perms":{"allow":["keiko.*"],"deny":[]}},"683272943769485370":{"groups":[],"perms":{"allow":["keiko.*"],"deny":[]}}}}